livigent_ca_patch/__init__.py
livigent_ca_patch/allow_1024.py
livigent_ca_patch-0.2.0.dist-info/LICENCE
livigent_ca_patch-0.2.0.dist-info/METADATA
livigent_ca_patch-0.2.0.dist-info/WHEEL
livigent_ca_patch-0.2.0.dist-info/top_level.txt
livigent_ca_patch-0.2.0.dist-info/RECORD
