Metadata-Version: 2.1
Name: livigent-ca-patch
Version: 0.2.0
Summary: Make requests, pip and dependant packages work on devices with Livigent.
Home-page: https://github.com/dickermoshe/livigent-ca-patch
Author: Moshe Dicker
Author-email: dickermoshe@gmail.com
License: GNU General Public License v3.0
Requires-Python: >=3.10
License-File: LICENCE
Requires-Dist: pip-system-certs
Requires-Dist: requests
